cvpy/__init__.py
cvpy/visualization.py
cvpy/annotation/__init__.py
cvpy/annotation/base/AnnotationLabel.py
cvpy/annotation/base/AnnotationType.py
cvpy/annotation/base/Credentials.py
cvpy/annotation/base/Project.py
cvpy/annotation/base/Task.py
cvpy/annotation/base/__init__.py
cvpy/annotation/cvat/CVATAuthenticator.py
cvpy/annotation/cvat/CVATProject.py
cvpy/annotation/cvat/CVATTask.py
cvpy/annotation/cvat/__init__.py
cvpy/base/CASServerMode.py
cvpy/base/CASThreadTunerResults.py
cvpy/base/ImageDataType.py
cvpy/base/ImageTable.py
cvpy/base/ImageType.py
cvpy/base/Statistic.py
cvpy/base/__init__.py
cvpy/biomedimage/BiomedImageTable.py
cvpy/biomedimage/LabelConnectivity.py
cvpy/biomedimage/__init__.py
cvpy/image/NaturalImageTable.py
cvpy/image/__init__.py
cvpy/tests/__init__.py
cvpy/tests/casutils.py
cvpy/tests/test_biomed_imagetable.py
cvpy/tests/test_casthreadtuner.py
cvpy/tests/test_credentials.py
cvpy/tests/test_cvat_authenticator.py
cvpy/tests/test_cvat_project.py
cvpy/tests/test_cvat_task.py
cvpy/tests/test_image_utils.py
cvpy/tests/test_imagetable.py
cvpy/tests/test_natural_imagetable.py
cvpy/utils/CASThreadTuner.py
cvpy/utils/ImageUtils.py
cvpy/utils/RandomNameGenerator.py
cvpy/utils/__init__.py
sas_cvpy-1.1.1.dist-info/LICENSE
sas_cvpy-1.1.1.dist-info/METADATA
sas_cvpy-1.1.1.dist-info/WHEEL
sas_cvpy-1.1.1.dist-info/top_level.txt
sas_cvpy-1.1.1.dist-info/RECORD
