Metadata-Version: 2.1
Name: sas-cvpy
Version: 1.1.1
Summary: SAS Computer Vision Interface
Home-page: https://github.com/sassoftware/python-cvpy
Author: SAS
Author-email: support@sas.com
License: Apache 2.0
Classifier: Development Status :: 5 - Production/Stable
Classifier: Environment :: Console
Classifier: Intended Audience :: Science/Research
Classifier: Programming Language :: Python :: 3.8
Classifier: Topic :: Scientific/Engineering
License-File: LICENSE
Requires-Dist: swat
Requires-Dist: PyQt5
Requires-Dist: pandas
Requires-Dist: numpy
Requires-Dist: matplotlib
Requires-Dist: mayavi
Requires-Dist: requests
